{
    "active_lock_reason": null,
    "assignee": {
        "avatar_url": "https://avatars.githubusercontent.com/u/10636986?v=4",
        "events_url": "https://api.github.com/users/rahku/events{/privacy}",
        "followers_url": "https://api.github.com/users/rahku/followers",
        "following_url": "https://api.github.com/users/rahku/following{/other_user}",
        "gists_url": "https://api.github.com/users/rahku/gists{/gist_id}",
        "gravatar_id": "",
        "html_url": "https://github.com/rahku",
        "id": 10636986,
        "login": "rahku",
        "node_id": "MDQ6VXNlcjEwNjM2OTg2",
        "organizations_url": "https://api.github.com/users/rahku/orgs",
        "received_events_url": "https://api.github.com/users/rahku/received_events",
        "repos_url": "https://api.github.com/users/rahku/repos",
        "site_admin": false,
        "starred_url": "https://api.github.com/users/rahku/starred{/owner}{/repo}",
        "subscriptions_url": "https://api.github.com/users/rahku/subscriptions",
        "type": "User",
        "url": "https://api.github.com/users/rahku"
    },
    "assignees": [
        {
            "avatar_url": "https://avatars.githubusercontent.com/u/10636986?v=4",
            "events_url": "https://api.github.com/users/rahku/events{/privacy}",
            "followers_url": "https://api.github.com/users/rahku/followers",
            "following_url": "https://api.github.com/users/rahku/following{/other_user}",
            "gists_url": "https://api.github.com/users/rahku/gists{/gist_id}",
            "gravatar_id": "",
            "html_url": "https://github.com/rahku",
            "id": 10636986,
            "login": "rahku",
            "node_id": "MDQ6VXNlcjEwNjM2OTg2",
            "organizations_url": "https://api.github.com/users/rahku/orgs",
            "received_events_url": "https://api.github.com/users/rahku/received_events",
            "repos_url": "https://api.github.com/users/rahku/repos",
            "site_admin": false,
            "starred_url": "https://api.github.com/users/rahku/starred{/owner}{/repo}",
            "subscriptions_url": "https://api.github.com/users/rahku/subscriptions",
            "type": "User",
            "url": "https://api.github.com/users/rahku"
        },
        {
            "avatar_url": "https://avatars.githubusercontent.com/u/11221966?v=4",
            "events_url": "https://api.github.com/users/amanbha/events{/privacy}",
            "followers_url": "https://api.github.com/users/amanbha/followers",
            "following_url": "https://api.github.com/users/amanbha/following{/other_user}",
            "gists_url": "https://api.github.com/users/amanbha/gists{/gist_id}",
            "gravatar_id": "",
            "html_url": "https://github.com/amanbha",
            "id": 11221966,
            "login": "amanbha",
            "node_id": "MDQ6VXNlcjExMjIxOTY2",
            "organizations_url": "https://api.github.com/users/amanbha/orgs",
            "received_events_url": "https://api.github.com/users/amanbha/received_events",
            "repos_url": "https://api.github.com/users/amanbha/repos",
            "site_admin": false,
            "starred_url": "https://api.github.com/users/amanbha/starred{/owner}{/repo}",
            "subscriptions_url": "https://api.github.com/users/amanbha/subscriptions",
            "type": "User",
            "url": "https://api.github.com/users/amanbha"
        },
        {
            "avatar_url": "https://avatars.githubusercontent.com/u/11344425?v=4",
            "events_url": "https://api.github.com/users/preethasubbarayalu/events{/privacy}",
            "followers_url": "https://api.github.com/users/preethasubbarayalu/followers",
            "following_url": "https://api.github.com/users/preethasubbarayalu/following{/other_user}",
            "gists_url": "https://api.github.com/users/preethasubbarayalu/gists{/gist_id}",
            "gravatar_id": "",
            "html_url": "https://github.com/preethasubbarayalu",
            "id": 11344425,
            "login": "preethasubbarayalu",
            "node_id": "MDQ6VXNlcjExMzQ0NDI1",
            "organizations_url": "https://api.github.com/users/preethasubbarayalu/orgs",
            "received_events_url": "https://api.github.com/users/preethasubbarayalu/received_events",
            "repos_url": "https://api.github.com/users/preethasubbarayalu/repos",
            "site_admin": false,
            "starred_url": "https://api.github.com/users/preethasubbarayalu/starred{/owner}{/repo}",
            "subscriptions_url": "https://api.github.com/users/preethasubbarayalu/subscriptions",
            "type": "User",
            "url": "https://api.github.com/users/preethasubbarayalu"
        }
    ],
    "author_association": "NONE",
    "body": "There is no update for the Microsoft.ServiceFabric.Data.Extensions package in nuget and therefore upgrading to 6.5 is not possible because the package has a constraint Microsoft.ServiceFabric.Data.Interfaces (= 3.3.664)",
    "closed_at": "2019-08-02T15:24:13Z",
    "closed_by": {
        "avatar_url": "https://avatars.githubusercontent.com/u/11221966?v=4",
        "events_url": "https://api.github.com/users/amanbha/events{/privacy}",
        "followers_url": "https://api.github.com/users/amanbha/followers",
        "following_url": "https://api.github.com/users/amanbha/following{/other_user}",
        "gists_url": "https://api.github.com/users/amanbha/gists{/gist_id}",
        "gravatar_id": "",
        "html_url": "https://github.com/amanbha",
        "id": 11221966,
        "login": "amanbha",
        "node_id": "MDQ6VXNlcjExMjIxOTY2",
        "organizations_url": "https://api.github.com/users/amanbha/orgs",
        "received_events_url": "https://api.github.com/users/amanbha/received_events",
        "repos_url": "https://api.github.com/users/amanbha/repos",
        "site_admin": false,
        "starred_url": "https://api.github.com/users/amanbha/starred{/owner}{/repo}",
        "subscriptions_url": "https://api.github.com/users/amanbha/subscriptions",
        "type": "User",
        "url": "https://api.github.com/users/amanbha"
    },
    "comments": 5,
    "comments_url": "https://api.github.com/repos/microsoft/service-fabric/issues/344/comments",
    "created_at": "2019-06-19T06:49:43Z",
    "events_url": "https://api.github.com/repos/microsoft/service-fabric/issues/344/events",
    "html_url": "https://github.com/microsoft/service-fabric/issues/344",
    "id": 457836615,
    "labels": [],
    "labels_url": "https://api.github.com/repos/microsoft/service-fabric/issues/344/labels{/name}",
    "locked": false,
    "milestone": null,
    "node_id": "MDU6SXNzdWU0NTc4MzY2MTU=",
    "number": 344,
    "performed_via_github_app": null,
    "reactions": {
        "+1": 0,
        "-1": 0,
        "confused": 0,
        "eyes": 0,
        "heart": 0,
        "hooray": 0,
        "laugh": 0,
        "rocket": 0,
        "total_count": 0,
        "url": "https://api.github.com/repos/microsoft/service-fabric/issues/344/reactions"
    },
    "repository_url": "https://api.github.com/repos/microsoft/service-fabric",
    "state": "closed",
    "state_reason": "completed",
    "timeline_url": "https://api.github.com/repos/microsoft/service-fabric/issues/344/timeline",
    "title": "Missing Microsoft.ServiceFabric.Data.Extensions nuget update",
    "updated_at": "2019-08-02T15:24:13Z",
    "url": "https://api.github.com/repos/microsoft/service-fabric/issues/344",
    "user": {
        "avatar_url": "https://avatars.githubusercontent.com/u/20299260?v=4",
        "events_url": "https://api.github.com/users/negberts/events{/privacy}",
        "followers_url": "https://api.github.com/users/negberts/followers",
        "following_url": "https://api.github.com/users/negberts/following{/other_user}",
        "gists_url": "https://api.github.com/users/negberts/gists{/gist_id}",
        "gravatar_id": "",
        "html_url": "https://github.com/negberts",
        "id": 20299260,
        "login": "negberts",
        "node_id": "MDQ6VXNlcjIwMjk5MjYw",
        "organizations_url": "https://api.github.com/users/negberts/orgs",
        "received_events_url": "https://api.github.com/users/negberts/received_events",
        "repos_url": "https://api.github.com/users/negberts/repos",
        "site_admin": false,
        "starred_url": "https://api.github.com/users/negberts/starred{/owner}{/repo}",
        "subscriptions_url": "https://api.github.com/users/negberts/subscriptions",
        "type": "User",
        "url": "https://api.github.com/users/negberts"
    }
}