{
    "active_lock_reason": null,
    "assignee": null,
    "assignees": [],
    "author_association": "CONTRIBUTOR",
    "body": "The documentation says\r\n\r\n> Used to set a callback function that is called when there is no activity on the `Http2Session` after `msecs` milliseconds.\r\n\r\nWhat exactly counts as \"activity\" there?",
    "closed_at": "2018-07-07T22:43:41Z",
    "closed_by": {
        "avatar_url": "https://avatars.githubusercontent.com/u/20809?v=4",
        "events_url": "https://api.github.com/users/apapirovski/events{/privacy}",
        "followers_url": "https://api.github.com/users/apapirovski/followers",
        "following_url": "https://api.github.com/users/apapirovski/following{/other_user}",
        "gists_url": "https://api.github.com/users/apapirovski/gists{/gist_id}",
        "gravatar_id": "",
        "html_url": "https://github.com/apapirovski",
        "id": 20809,
        "login": "apapirovski",
        "node_id": "MDQ6VXNlcjIwODA5",
        "organizations_url": "https://api.github.com/users/apapirovski/orgs",
        "received_events_url": "https://api.github.com/users/apapirovski/received_events",
        "repos_url": "https://api.github.com/users/apapirovski/repos",
        "site_admin": false,
        "starred_url": "https://api.github.com/users/apapirovski/starred{/owner}{/repo}",
        "subscriptions_url": "https://api.github.com/users/apapirovski/subscriptions",
        "type": "User",
        "url": "https://api.github.com/users/apapirovski"
    },
    "comments": 4,
    "comments_url": "https://api.github.com/repos/nodejs/node/issues/21582/comments",
    "created_at": "2018-06-28T21:28:46Z",
    "events_url": "https://api.github.com/repos/nodejs/node/issues/21582/events",
    "html_url": "https://github.com/nodejs/node/issues/21582",
    "id": 336786604,
    "labels": [
        {
            "color": "c2e0c6",
            "default": false,
            "description": "Issues or PRs related to the http2 subsystem.",
            "id": 647282877,
            "name": "http2",
            "node_id": "MDU6TGFiZWw2NDcyODI4Nzc=",
            "url": "https://api.github.com/repos/nodejs/node/labels/http2"
        }
    ],
    "labels_url": "https://api.github.com/repos/nodejs/node/issues/21582/labels{/name}",
    "locked": false,
    "milestone": null,
    "node_id": "MDU6SXNzdWUzMzY3ODY2MDQ=",
    "number": 21582,
    "performed_via_github_app": null,
    "reactions": {
        "+1": 0,
        "-1": 0,
        "confused": 0,
        "eyes": 0,
        "heart": 0,
        "hooray": 0,
        "laugh": 0,
        "rocket": 0,
        "total_count": 0,
        "url": "https://api.github.com/repos/nodejs/node/issues/21582/reactions"
    },
    "repository_url": "https://api.github.com/repos/nodejs/node",
    "state": "closed",
    "state_reason": "completed",
    "timeline_url": "https://api.github.com/repos/nodejs/node/issues/21582/timeline",
    "title": "What counts as \"activity\" for Http2Session#setTimeout?",
    "updated_at": "2018-07-07T22:43:41Z",
    "url": "https://api.github.com/repos/nodejs/node/issues/21582",
    "user": {
        "avatar_url": "https://avatars.githubusercontent.com/u/961599?v=4",
        "events_url": "https://api.github.com/users/murgatroid99/events{/privacy}",
        "followers_url": "https://api.github.com/users/murgatroid99/followers",
        "following_url": "https://api.github.com/users/murgatroid99/following{/other_user}",
        "gists_url": "https://api.github.com/users/murgatroid99/gists{/gist_id}",
        "gravatar_id": "",
        "html_url": "https://github.com/murgatroid99",
        "id": 961599,
        "login": "murgatroid99",
        "node_id": "MDQ6VXNlcjk2MTU5OQ==",
        "organizations_url": "https://api.github.com/users/murgatroid99/orgs",
        "received_events_url": "https://api.github.com/users/murgatroid99/received_events",
        "repos_url": "https://api.github.com/users/murgatroid99/repos",
        "site_admin": false,
        "starred_url": "https://api.github.com/users/murgatroid99/starred{/owner}{/repo}",
        "subscriptions_url": "https://api.github.com/users/murgatroid99/subscriptions",
        "type": "User",
        "url": "https://api.github.com/users/murgatroid99"
    }
}