{
    "active_lock_reason": null,
    "assignee": null,
    "assignees": [],
    "author_association": "NONE",
    "body": "### Description of Issue/Question\r\nTagging @cedwards at his request.\r\n\r\nTested on both FreeBSD 11.1 and 10.4:\r\n```\r\nroot@salt6:~ # cat /etc/rc.conf\r\nec2_configinit_enable=YES\r\nec2_fetchkey_enable=YES\r\nec2_ephemeralswap_enable=YES\r\nec2_loghostkey_enable=YES\r\nfirstboot_freebsd_update_enable=YES\r\nfirstboot_pkgs_enable=YES\r\ngrowfs_enable=\"YES\"\r\nifconfig_DEFAULT=\"SYNCDHCP accept_rtadv\"\r\nsshd_enable=\"YES\"\r\nfirstboot_pkgs_list=\"awscli\"\r\nipv6_activate_all_interfaces=\"YES\"\r\ndhclient_program=\"/usr/local/sbin/dual-dhclient\"\r\nhostname=\"salt6\"\r\n\r\nroot@salt6:~ # salt-call service.enable salt_master\r\nlocal:\r\n    True\r\n\r\nroot@salt6:~ # cat /etc/rc.conf\r\nec2_configinit_enable=YESec2_fetchkey_enable=YESec2_ephemeralswap_enable=YESec2_loghostkey_enable=YESfirstboot_freebsd_update_enable=YESfirstboot_pkgs_enable=YESgrowfs_enable=\"YES\"ifconfig_DEFAULT=\"SYNCDHCPaccept_rtadv\"sshd_enable=\"YES\"firstboot_pkgs_list=\"awscli\"ipv6_activate_all_interfaces=\"YES\"dhclient_program=\"/usr/local/sbin/dual-dhclient\"hostname=\"salt6\"\r\nsalt_master_enable=\"YES\"\r\n\r\nroot@salt6:~ # pkg info | grep salt\r\npy27-salt-2018.3.0_1           Distributed remote execution and configuration management system\r\nroot@salt6:~ #\r\n```\r\n### Setup\r\nNone. This is a vanilla install, fresh out of the box.\r\n\r\n### Steps to Reproduce Issue\r\n```\r\npkg install py-salt\r\nsalt-call service.enable salt_master\r\n```\r\n### Versions Report\r\n```\r\nroot@salt6:~ # salt --versions-report\r\nSalt Version:\r\n           Salt: 2018.3.0\r\n\r\nDependency Versions:\r\n           cffi: 1.11.5\r\n       cherrypy: Not Installed\r\n       dateutil: Not Installed\r\n      docker-py: Not Installed\r\n          gitdb: Not Installed\r\n      gitpython: Not Installed\r\n          ioflo: Not Installed\r\n         Jinja2: 2.10\r\n        libgit2: Not Installed\r\n        libnacl: Not Installed\r\n       M2Crypto: Not Installed\r\n           Mako: Not Installed\r\n   msgpack-pure: Not Installed\r\n msgpack-python: 0.5.6\r\n   mysql-python: Not Installed\r\n      pycparser: 2.18\r\n       pycrypto: 2.6.1\r\n   pycryptodome: Not Installed\r\n         pygit2: Not Installed\r\n         Python: 2.7.15 (default, Jun  1 2018, 20:05:17)\r\n   python-gnupg: Not Installed\r\n         PyYAML: 3.12\r\n          PyZMQ: 17.0.0\r\n           RAET: Not Installed\r\n          smmap: Not Installed\r\n        timelib: Not Installed\r\n        Tornado: 4.5.3\r\n            ZMQ: 4.2.3\r\n\r\nSystem Versions:\r\n           dist:\r\n         locale: US-ASCII\r\n        machine: amd64\r\n        release: 11.1-RELEASE-p10\r\n         system: FreeBSD\r\n        version: Not Installed\r\n\r\nroot@salt6:~ #\r\n```",
    "closed_at": "2018-06-09T18:26:51Z",
    "closed_by": {
        "avatar_url": "https://avatars.githubusercontent.com/u/732321?v=4",
        "events_url": "https://api.github.com/users/gtmanfred/events{/privacy}",
        "followers_url": "https://api.github.com/users/gtmanfred/followers",
        "following_url": "https://api.github.com/users/gtmanfred/following{/other_user}",
        "gists_url": "https://api.github.com/users/gtmanfred/gists{/gist_id}",
        "gravatar_id": "",
        "html_url": "https://github.com/gtmanfred",
        "id": 732321,
        "login": "gtmanfred",
        "node_id": "MDQ6VXNlcjczMjMyMQ==",
        "organizations_url": "https://api.github.com/users/gtmanfred/orgs",
        "received_events_url": "https://api.github.com/users/gtmanfred/received_events",
        "repos_url": "https://api.github.com/users/gtmanfred/repos",
        "site_admin": false,
        "starred_url": "https://api.github.com/users/gtmanfred/starred{/owner}{/repo}",
        "subscriptions_url": "https://api.github.com/users/gtmanfred/subscriptions",
        "type": "User",
        "url": "https://api.github.com/users/gtmanfred"
    },
    "comments": 6,
    "comments_url": "https://api.github.com/repos/saltstack/salt/issues/48036/comments",
    "created_at": "2018-06-08T16:44:40Z",
    "events_url": "https://api.github.com/repos/saltstack/salt/issues/48036/events",
    "html_url": "https://github.com/saltstack/salt/issues/48036",
    "id": 330728656,
    "labels": [
        {
            "color": "c7def8",
            "default": false,
            "description": "Duplicate of another issue or PR - will be closed",
            "id": 41662302,
            "name": "Duplicate",
            "node_id": "MDU6TGFiZWw0MTY2MjMwMg==",
            "url": "https://api.github.com/repos/saltstack/salt/labels/Duplicate"
        }
    ],
    "labels_url": "https://api.github.com/repos/saltstack/salt/issues/48036/labels{/name}",
    "locked": false,
    "milestone": {
        "closed_at": null,
        "closed_issues": 4445,
        "created_at": "2013-05-28T22:24:12Z",
        "creator": {
            "avatar_url": "https://avatars.githubusercontent.com/u/702318?v=4",
            "events_url": "https://api.github.com/users/basepi/events{/privacy}",
            "followers_url": "https://api.github.com/users/basepi/followers",
            "following_url": "https://api.github.com/users/basepi/following{/other_user}",
            "gists_url": "https://api.github.com/users/basepi/gists{/gist_id}",
            "gravatar_id": "",
            "html_url": "https://github.com/basepi",
            "id": 702318,
            "login": "basepi",
            "node_id": "MDQ6VXNlcjcwMjMxOA==",
            "organizations_url": "https://api.github.com/users/basepi/orgs",
            "received_events_url": "https://api.github.com/users/basepi/received_events",
            "repos_url": "https://api.github.com/users/basepi/repos",
            "site_admin": false,
            "starred_url": "https://api.github.com/users/basepi/starred{/owner}{/repo}",
            "subscriptions_url": "https://api.github.com/users/basepi/subscriptions",
            "type": "User",
            "url": "https://api.github.com/users/basepi"
        },
        "description": "Issues which are blocked in some way, whether they need further discussion, clarification, justification, or are blocked for some other reason.",
        "due_on": null,
        "html_url": "https://github.com/saltstack/salt/milestone/37",
        "id": 343741,
        "labels_url": "https://api.github.com/repos/saltstack/salt/milestones/37/labels",
        "node_id": "MDk6TWlsZXN0b25lMzQzNzQx",
        "number": 37,
        "open_issues": 200,
        "state": "open",
        "title": "Blocked",
        "updated_at": "2023-04-19T16:43:04Z",
        "url": "https://api.github.com/repos/saltstack/salt/milestones/37"
    },
    "node_id": "MDU6SXNzdWUzMzA3Mjg2NTY=",
    "number": 48036,
    "performed_via_github_app": null,
    "reactions": {
        "+1": 0,
        "-1": 0,
        "confused": 0,
        "eyes": 0,
        "heart": 0,
        "hooray": 0,
        "laugh": 0,
        "rocket": 0,
        "total_count": 0,
        "url": "https://api.github.com/repos/saltstack/salt/issues/48036/reactions"
    },
    "repository_url": "https://api.github.com/repos/saltstack/salt",
    "state": "closed",
    "state_reason": "completed",
    "timeline_url": "https://api.github.com/repos/saltstack/salt/issues/48036/timeline",
    "title": "Salt 2018.3.0 service.enable mangles /etc/rc.conf, rendering system unbootable",
    "updated_at": "2018-06-09T18:31:16Z",
    "url": "https://api.github.com/repos/saltstack/salt/issues/48036",
    "user": {
        "avatar_url": "https://avatars.githubusercontent.com/u/2323891?v=4",
        "events_url": "https://api.github.com/users/JamesSnow/events{/privacy}",
        "followers_url": "https://api.github.com/users/JamesSnow/followers",
        "following_url": "https://api.github.com/users/JamesSnow/following{/other_user}",
        "gists_url": "https://api.github.com/users/JamesSnow/gists{/gist_id}",
        "gravatar_id": "",
        "html_url": "https://github.com/JamesSnow",
        "id": 2323891,
        "login": "JamesSnow",
        "node_id": "MDQ6VXNlcjIzMjM4OTE=",
        "organizations_url": "https://api.github.com/users/JamesSnow/orgs",
        "received_events_url": "https://api.github.com/users/JamesSnow/received_events",
        "repos_url": "https://api.github.com/users/JamesSnow/repos",
        "site_admin": false,
        "starred_url": "https://api.github.com/users/JamesSnow/starred{/owner}{/repo}",
        "subscriptions_url": "https://api.github.com/users/JamesSnow/subscriptions",
        "type": "User",
        "url": "https://api.github.com/users/JamesSnow"
    }
}