{
    "active_lock_reason": null,
    "assignee": null,
    "assignees": [],
    "author_association": "COLLABORATOR",
    "body": "The docs inaccurately stated that custom module types were synced when `state.apply` is run, but this is only the case when run without SLS targets (i.e. when a highstate is run). This PR does the following:\r\n\r\n1. Updates the docs\r\n\r\n2. Adds a \"sync\" argument to provide the functionality that the docs suggested was already present\r\n\r\nResolves #48025.",
    "closed_at": "2018-06-21T19:57:03Z",
    "closed_by": {
        "avatar_url": "https://avatars.githubusercontent.com/u/6547906?v=4",
        "events_url": "https://api.github.com/users/rallytime/events{/privacy}",
        "followers_url": "https://api.github.com/users/rallytime/followers",
        "following_url": "https://api.github.com/users/rallytime/following{/other_user}",
        "gists_url": "https://api.github.com/users/rallytime/gists{/gist_id}",
        "gravatar_id": "",
        "html_url": "https://github.com/rallytime",
        "id": 6547906,
        "login": "rallytime",
        "node_id": "MDQ6VXNlcjY1NDc5MDY=",
        "organizations_url": "https://api.github.com/users/rallytime/orgs",
        "received_events_url": "https://api.github.com/users/rallytime/received_events",
        "repos_url": "https://api.github.com/users/rallytime/repos",
        "site_admin": false,
        "starred_url": "https://api.github.com/users/rallytime/starred{/owner}{/repo}",
        "subscriptions_url": "https://api.github.com/users/rallytime/subscriptions",
        "type": "User",
        "url": "https://api.github.com/users/rallytime"
    },
    "comments": 3,
    "comments_url": "https://api.github.com/repos/saltstack/salt/issues/48037/comments",
    "created_at": "2018-06-08T17:37:39Z",
    "draft": false,
    "events_url": "https://api.github.com/repos/saltstack/salt/issues/48037/events",
    "html_url": "https://github.com/saltstack/salt/pull/48037",
    "id": 330744305,
    "labels": [],
    "labels_url": "https://api.github.com/repos/saltstack/salt/issues/48037/labels{/name}",
    "locked": false,
    "milestone": null,
    "node_id": "MDExOlB1bGxSZXF1ZXN0MTkzNjc5MTQ0",
    "number": 48037,
    "performed_via_github_app": null,
    "pull_request": {
        "diff_url": "https://github.com/saltstack/salt/pull/48037.diff",
        "html_url": "https://github.com/saltstack/salt/pull/48037",
        "merged_at": "2018-06-21T19:57:03Z",
        "patch_url": "https://github.com/saltstack/salt/pull/48037.patch",
        "url": "https://api.github.com/repos/saltstack/salt/pulls/48037"
    },
    "reactions": {
        "+1": 0,
        "-1": 0,
        "confused": 0,
        "eyes": 0,
        "heart": 0,
        "hooray": 0,
        "laugh": 0,
        "rocket": 0,
        "total_count": 0,
        "url": "https://api.github.com/repos/saltstack/salt/issues/48037/reactions"
    },
    "repository_url": "https://api.github.com/repos/saltstack/salt",
    "state": "closed",
    "state_reason": null,
    "timeline_url": "https://api.github.com/repos/saltstack/salt/issues/48037/timeline",
    "title": "Add \"sync_mods\" argument to state.apply/state.sls",
    "updated_at": "2018-06-24T21:43:11Z",
    "url": "https://api.github.com/repos/saltstack/salt/issues/48037",
    "user": {
        "avatar_url": "https://avatars.githubusercontent.com/u/328598?v=4",
        "events_url": "https://api.github.com/users/terminalmage/events{/privacy}",
        "followers_url": "https://api.github.com/users/terminalmage/followers",
        "following_url": "https://api.github.com/users/terminalmage/following{/other_user}",
        "gists_url": "https://api.github.com/users/terminalmage/gists{/gist_id}",
        "gravatar_id": "",
        "html_url": "https://github.com/terminalmage",
        "id": 328598,
        "login": "terminalmage",
        "node_id": "MDQ6VXNlcjMyODU5OA==",
        "organizations_url": "https://api.github.com/users/terminalmage/orgs",
        "received_events_url": "https://api.github.com/users/terminalmage/received_events",
        "repos_url": "https://api.github.com/users/terminalmage/repos",
        "site_admin": false,
        "starred_url": "https://api.github.com/users/terminalmage/starred{/owner}{/repo}",
        "subscriptions_url": "https://api.github.com/users/terminalmage/subscriptions",
        "type": "User",
        "url": "https://api.github.com/users/terminalmage"
    }
}