{
    "active_lock_reason": null,
    "assignee": null,
    "assignees": [],
    "author_association": "CONTRIBUTOR",
    "body": "# Campbell color scheme should change the foreground color from #F2F2F2 to #CCCCCC\r\n\r\nThe problem with the current Campbell color scheme is that it has no range for the default terminal \"white.\" ESC[m, ESC[97m, ESC[1m, ESC[1;30m, and ESC[1;37m are all the same #F2F2F2 color, \"brightWhite.\" Just changing the foreground from \"brightWhite\" to \"white\" means that ESC[m, and ESC[37m are shown as \"white\" while ESC[1m, ESC[1;30m, and ESC[1;37m are \"brightWhite.\" When you consider what these values mean, it really makes sense that this is how the scheme should be defined. Looking at the intersection of 37m/47m you can see how this really stands out in the current scheme as it breaks the diagonal. With the current Campbell color scheme, you can't even address \"white\" except as a background color.\r\n\r\nCurrent Campbell:\r\n![image](https://user-images.githubusercontent.com/3703112/59894380-434c6100-9395-11e9-8a9e-443e48e9a603.png)\r\n\r\nProposed Campbell:\r\n![image](https://user-images.githubusercontent.com/3703112/59894392-4f382300-9395-11e9-8784-3531a5d5a86e.png)\r\n\r\n# Proposed technical implementation details\r\n\r\n```JSON\r\n{\r\n  \"schemes\" :\r\n  [\r\n    {\r\n      \"background\" : \"#0C0C0C\",\r\n      \"black\" : \"#0C0C0C\",\r\n      \"blue\" : \"#0037DA\",\r\n      \"brightBlack\" : \"#767676\",\r\n      \"brightBlue\" : \"#3B78FF\",\r\n      \"brightCyan\" : \"#61D6D6\",\r\n      \"brightGreen\" : \"#16C60C\",\r\n      \"brightPurple\" : \"#B4009E\",\r\n      \"brightRed\" : \"#E74856\",\r\n      \"brightWhite\" : \"#F2F2F2\",\r\n      \"brightYellow\" : \"#F9F1A5\",\r\n      \"cyan\" : \"#3A96DD\",\r\n      \"foreground\" : \"#CCCCCC\",\r\n      \"green\" : \"#13A10E\",\r\n      \"name\" : \"Campbell\",\r\n      \"purple\" : \"#881798\",\r\n      \"red\" : \"#C50F1F\",\r\n      \"white\" : \"#CCCCCC\",\r\n      \"yellow\" : \"#C19C00\"\r\n    }\r\n  ]\r\n}\r\n",
    "closed_at": "2019-06-29T01:19:42Z",
    "closed_by": {
        "avatar_url": "https://avatars.githubusercontent.com/u/14316954?v=4",
        "events_url": "https://api.github.com/users/DHowett-MSFT/events{/privacy}",
        "followers_url": "https://api.github.com/users/DHowett-MSFT/followers",
        "following_url": "https://api.github.com/users/DHowett-MSFT/following{/other_user}",
        "gists_url": "https://api.github.com/users/DHowett-MSFT/gists{/gist_id}",
        "gravatar_id": "",
        "html_url": "https://github.com/DHowett-MSFT",
        "id": 14316954,
        "login": "DHowett-MSFT",
        "node_id": "MDQ6VXNlcjE0MzE2OTU0",
        "organizations_url": "https://api.github.com/users/DHowett-MSFT/orgs",
        "received_events_url": "https://api.github.com/users/DHowett-MSFT/received_events",
        "repos_url": "https://api.github.com/users/DHowett-MSFT/repos",
        "site_admin": false,
        "starred_url": "https://api.github.com/users/DHowett-MSFT/starred{/owner}{/repo}",
        "subscriptions_url": "https://api.github.com/users/DHowett-MSFT/subscriptions",
        "type": "User",
        "url": "https://api.github.com/users/DHowett-MSFT"
    },
    "comments": 5,
    "comments_url": "https://api.github.com/repos/microsoft/terminal/issues/1363/comments",
    "created_at": "2019-06-21T03:13:40Z",
    "events_url": "https://api.github.com/repos/microsoft/terminal/issues/1363/events",
    "html_url": "https://github.com/microsoft/terminal/issues/1363",
    "id": 458986888,
    "labels": [
        {
            "color": "0e8a16",
            "default": false,
            "description": "It's available in an Insiders build or a release",
            "id": 679112164,
            "name": "Resolution-Fix-Available",
            "node_id": "MDU6TGFiZWw2NzkxMTIxNjQ=",
            "url": "https://api.github.com/repos/microsoft/terminal/labels/Resolution-Fix-Available"
        },
        {
            "color": "13d3ea",
            "default": false,
            "description": "We encourage anyone to jump in on these.",
            "id": 835408524,
            "name": "Help Wanted",
            "node_id": "MDU6TGFiZWw4MzU0MDg1MjQ=",
            "url": "https://api.github.com/repos/microsoft/terminal/labels/Help%20Wanted"
        },
        {
            "color": "005ab4",
            "default": false,
            "description": "Issues related to settings and customizability, for console or terminal",
            "id": 1355048958,
            "name": "Area-Settings",
            "node_id": "MDU6TGFiZWwxMzU1MDQ4OTU4",
            "url": "https://api.github.com/repos/microsoft/terminal/labels/Area-Settings"
        },
        {
            "color": "891b89",
            "default": false,
            "description": "The product is the management of the products.",
            "id": 1364969395,
            "name": "Product-Meta",
            "node_id": "MDU6TGFiZWwxMzY0OTY5Mzk1",
            "url": "https://api.github.com/repos/microsoft/terminal/labels/Product-Meta"
        },
        {
            "color": "fdff00",
            "default": false,
            "description": "It's a feature request, but it doesn't really need a major design.",
            "id": 1365259249,
            "name": "Issue-Task",
            "node_id": "MDU6TGFiZWwxMzY1MjU5MjQ5",
            "url": "https://api.github.com/repos/microsoft/terminal/labels/Issue-Task"
        }
    ],
    "labels_url": "https://api.github.com/repos/microsoft/terminal/issues/1363/labels{/name}",
    "locked": false,
    "milestone": null,
    "node_id": "MDU6SXNzdWU0NTg5ODY4ODg=",
    "number": 1363,
    "performed_via_github_app": null,
    "reactions": {
        "+1": 2,
        "-1": 0,
        "confused": 0,
        "eyes": 0,
        "heart": 0,
        "hooray": 0,
        "laugh": 0,
        "rocket": 0,
        "total_count": 2,
        "url": "https://api.github.com/repos/microsoft/terminal/issues/1363/reactions"
    },
    "repository_url": "https://api.github.com/repos/microsoft/terminal",
    "state": "closed",
    "state_reason": "completed",
    "timeline_url": "https://api.github.com/repos/microsoft/terminal/issues/1363/timeline",
    "title": "Campbell color scheme should change the foreground color from #F2F2F2 to #CCCCCC",
    "updated_at": "2019-08-03T01:48:11Z",
    "url": "https://api.github.com/repos/microsoft/terminal/issues/1363",
    "user": {
        "avatar_url": "https://avatars.githubusercontent.com/u/3703112?v=4",
        "events_url": "https://api.github.com/users/rbeesley/events{/privacy}",
        "followers_url": "https://api.github.com/users/rbeesley/followers",
        "following_url": "https://api.github.com/users/rbeesley/following{/other_user}",
        "gists_url": "https://api.github.com/users/rbeesley/gists{/gist_id}",
        "gravatar_id": "",
        "html_url": "https://github.com/rbeesley",
        "id": 3703112,
        "login": "rbeesley",
        "node_id": "MDQ6VXNlcjM3MDMxMTI=",
        "organizations_url": "https://api.github.com/users/rbeesley/orgs",
        "received_events_url": "https://api.github.com/users/rbeesley/received_events",
        "repos_url": "https://api.github.com/users/rbeesley/repos",
        "site_admin": false,
        "starred_url": "https://api.github.com/users/rbeesley/starred{/owner}{/repo}",
        "subscriptions_url": "https://api.github.com/users/rbeesley/subscriptions",
        "type": "User",
        "url": "https://api.github.com/users/rbeesley"
    }
}